openai_chatbot_project/__init__.py
openai_chatbot_project/__main__.py
openai_chatbot_project/openai_chatbot.py
vinbot-0.0.1.dist-info/METADATA
vinbot-0.0.1.dist-info/WHEEL
vinbot-0.0.1.dist-info/entry_points.txt
vinbot-0.0.1.dist-info/top_level.txt
vinbot-0.0.1.dist-info/RECORD
