Metadata-Version: 2.1
Name: vinbot
Version: 0.0.1
Summary: A one line description of your project.
Home-page: https://github.com/yourusername/your-repo.git
Author: VinnyVanGogh
Author-email: VinnyVanGogh <your_email@example.com>
License: MIT
Project-URL: Homepage, https://github.com/yourusername/your-repo.git
Requires-Python: >=3.10
